uttt
