Metadata-Version: 1.0
Name: uttt
Version: 0.3-2
Summary: An Ultimate Tic Tac Toe Class
Home-page: http://github.com/projectdelphai/uttt_irc
Author: projectdelphai
Author-email: projectdelphai@gmail.com
License: MIT
Platform: UNKNOWN
